braze_sdk/__init__.py
braze_sdk/clients.py
braze_sdk-1.0.1.dist-info/LICENSE
braze_sdk-1.0.1.dist-info/METADATA
braze_sdk-1.0.1.dist-info/WHEEL
braze_sdk-1.0.1.dist-info/top_level.txt
braze_sdk-1.0.1.dist-info/RECORD
