Metadata-Version: 2.1
Name: braze-sdk
Version: 1.0.1
Summary: Braze Python 3 SDK.
Home-page: https://github.com/paulokuong/braze
Author: Paulo Kuong
Author-email: UNKNOWN
License: MIT
Keywords: Braze API
Platform: UNKNOWN
